setup.cfg
setup.py
komaru_API/__init__.py
komaru_API.egg-info/PKG-INFO
komaru_API.egg-info/SOURCES.txt
komaru_API.egg-info/dependency_links.txt
komaru_API.egg-info/not-zip-safe
komaru_API.egg-info/top_level.txt