Metadata-Version: 2.1
Name: komaru-API
Version: 0.11.post20231009
Summary: GET RANDOM KOMARU FOR FAST
Author-email: itzskyreed@gmail.com
